neopipe/__about__.py
neopipe/__init__.py
neopipe/async_pipeline.py
neopipe/pipeline.py
neopipe/result.py
neopipe/sync_pipeline.py
neopipe/task.py
neopipe/workflow.py
neopipe-0.1.4.dist-info/METADATA
neopipe-0.1.4.dist-info/WHEEL
neopipe-0.1.4.dist-info/licenses/LICENSE
neopipe-0.1.4.dist-info/RECORD
