Metadata-Version: 2.4
Name: neopipe
Version: 0.1.4
Summary: A Python library for seamless function orchestration, Designed to streamline workflow management in microservices and AI-powered applications
Project-URL: Documentation, https://mrdatapsycho.github.io/neopipe
Project-URL: Issues, https://github.com/MrDataPsycho/neopipe/issues
Project-URL: Source, https://github.com/MrDataPsycho/neopipe
Author-email: MrDataPsycho <mr.data.psycho@gmail.com>
License-Expression: MIT
License-File: LICENSE
Keywords: function,orchestration,pipeline
Classifier: Programming Language :: Python
Classifier: Programming Language :: Python :: 3.10
Classifier: Programming Language :: Python :: 3.11
Classifier: Programming Language :: Python :: 3.12
Classifier: Programming Language :: Python :: Implementation :: CPython
Classifier: Programming Language :: Python :: Implementation :: PyPy
Requires-Python: >=3.10
Provides-Extra: dev
Requires-Dist: isort; extra == 'dev'
Requires-Dist: mypy; extra == 'dev'
Requires-Dist: ruff; extra == 'dev'
Provides-Extra: docs
Requires-Dist: mkdocs; extra == 'docs'
Requires-Dist: mkdocs-material; extra == 'docs'
Requires-Dist: mkdocstrings[python]; extra == 'docs'
Provides-Extra: example
Requires-Dist: dotenv; extra == 'example'
Requires-Dist: httpx; extra == 'example'
Requires-Dist: openai; extra == 'example'
Requires-Dist: pydantic; extra == 'example'
Provides-Extra: testing
Requires-Dist: pytest; extra == 'testing'
Requires-Dist: pytest-asyncio; extra == 'testing'
Requires-Dist: pytest-cov; extra == 'testing'
Requires-Dist: pytest-mock; extra == 'testing'
